richdisplay/__init__.py
richdisplay/state.py
richdisplay/core/__init__.py
richdisplay/core/display.py
richdisplay/core/log_control.py
richdisplay/database/__init__.py
richdisplay/database/log_db.py
richdisplay/database/log_query.py
richdisplay/exporters/__init__.py
richdisplay/exporters/csv_exporter.py
richdisplay/exporters/json_exporter.py
richdisplay/utils/__init__.py
richdisplay/utils/formatter.py
richdisplay-0.2.0.dist-info/licenses/LICENCE
richdisplay-0.2.0.dist-info/METADATA
richdisplay-0.2.0.dist-info/WHEEL
richdisplay-0.2.0.dist-info/top_level.txt
richdisplay-0.2.0.dist-info/RECORD
