Metadata-Version: 2.4
Name: richdisplay
Version: 0.2.0
Summary: Context-aware CLI logging and display toolkit using Rich and SQLite.
Author-email: Hendrik Siemens <siemenshendrik1@gmail.com>
Project-URL: Homepage, https://github.com/SiemensHalske/pydisplay
Project-URL: Bug Tracker, https://github.com/SiemensHalske/pydisplay/issues
Requires-Python: >=3.8
License-File: LICENCE
Requires-Dist: rich>=13.0
Dynamic: license-file
